sshconfig/__init__.py
sshconfig/command.py
sshconfig/core.py
sshconfig/help.py
sshconfig/main.py
sshconfig/preferences.py
sshconfig/python.py
sshconfig/settings.py
sshconfig/sshconfig.py
sshconfig/utilities.py
sshconfig-2.2.dist-info/LICENSE
sshconfig-2.2.dist-info/METADATA
sshconfig-2.2.dist-info/WHEEL
sshconfig-2.2.dist-info/entry_points.txt
sshconfig-2.2.dist-info/top_level.txt
sshconfig-2.2.dist-info/zip-safe
sshconfig-2.2.dist-info/RECORD
