Metadata-Version: 2.1
Name: sshconfig
Version: 2.2
Summary: SSH config file generator
Home-page: https://sshconfig.readthedocs.io
Download-URL: https://github.com/kenkundert/sshconfig/tarball/master
Author: Ken Kundert
Author-email: sshconfig@nurdletech.com
License: GPLv3+
Keywords: ssh
Classifier: Development Status :: 5 - Production/Stable
Classifier: Intended Audience :: Developers
Classifier: License :: OSI Approved :: GNU General Public License v3 or later (GPLv3+)
Classifier: Natural Language :: English
Classifier: Operating System :: POSIX :: Linux
Classifier: Programming Language :: Python :: 3.6
Classifier: Programming Language :: Python :: 3.7
Classifier: Programming Language :: Python :: 3.8
Classifier: Programming Language :: Python :: 3.9
Classifier: Programming Language :: Python :: 3.10
Classifier: Topic :: Utilities
Requires-Python: >=3.6
License-File: LICENSE
Requires-Dist: appdirs
Requires-Dist: arrow
Requires-Dist: docopt
Requires-Dist: inform
Requires-Dist: shlib
